.bumpversion.cfg
.gitignore
LICENSE
MANIFEST.in
README.md
setup.cfg
setup.py
docassemble/__init__.py
docassemble.lscrefer.egg-info/PKG-INFO
docassemble.lscrefer.egg-info/SOURCES.txt
docassemble.lscrefer.egg-info/dependency_links.txt
docassemble.lscrefer.egg-info/namespace_packages.txt
docassemble.lscrefer.egg-info/not-zip-safe
docassemble.lscrefer.egg-info/top_level.txt
docassemble/lscrefer/__init__.py
docassemble/lscrefer/lsc.py
docassemble/lscrefer/data/sources/Programs.json
docassemble/lscrefer/data/sources/README.md
docassemble/lscrefer/data/sources/poverty.yml
docassemble/lscrefer/data/static/README.md
docassemble/lscrefer/data/templates/README.md