Metadata-Version: 2.1
Name: docassemble.lscrefer
Version: 0.0.13
Summary: A module to assist with referring users to LSC programs.
Home-page: https://philalegal.org
Author: Jonathan Pyle
Author-email: jpyle@philalegal.org
License: The MIT License (MIT)
License-File: LICENSE
